astrochem_ml/__init__.py
astrochem_ml/classes.py
astrochem_ml/cli.py
astrochem_ml/smiles/__init__.py
astrochem_ml/smiles/classes.py
astrochem_ml/smiles/functionals.py
astrochem_ml/smiles/isotopes.py
astrochem_ml/smiles/misc.py
astrochem_ml/smiles/tests/__init__.py
astrochem_ml/smiles/tests/test_functionals.py
astrochem_ml/smiles/tests/test_generator.py
astrochem_ml/smiles/tests/test_isotopes.py
astrochem_ml-0.1.1.dist-info/LICENSE
astrochem_ml-0.1.1.dist-info/WHEEL
astrochem_ml-0.1.1.dist-info/METADATA
astrochem_ml-0.1.1.dist-info/RECORD
